thonnycontrib/memorycode/__init__.py
thonnycontrib/memorycode/log.py
thonnycontrib/memorycode/memorycode.py
thonnycontrib/memorycode/memorycodeView.py
thonnycontrib/memorycode/repoManager.py
memorycode-0.1.3.dist-info/METADATA
memorycode-0.1.3.dist-info/WHEEL
memorycode-0.1.3.dist-info/top_level.txt
memorycode-0.1.3.dist-info/RECORD
