Metadata-Version: 2.1
Name: memorycode
Version: 0.1.3
Summary: Memorycode
Home-page: https://github.com/journalisation/thonny-memorycode
Author: Jerome Amiguet
Classifier: Programming Language :: Python :: 3
Classifier: License :: OSI Approved :: BSD License
Classifier: Intended Audience :: Education
Requires-Python: >=3.6
Requires-Dist: GitPython
